package com.aspose.cells;

class zalp
{
  /* Error */
  static void a(Workbook paramWorkbook, LoadOptions paramLoadOptions)
    throws java.lang.Exception
  {
    // Byte code:
    //   0: aload_0
    //   1: invokevirtual 14	com/aspose/cells/Workbook:getSettings	()Lcom/aspose/cells/WorkbookSettings;
    //   4: iconst_1
    //   5: putfield 12	com/aspose/cells/WorkbookSettings:f	Z
    //   8: new 5	com/aspose/cells/zalq
    //   11: dup
    //   12: aload_0
    //   13: aload_1
    //   14: invokespecial 15	com/aspose/cells/zalq:<init>	(Lcom/aspose/cells/Workbook;Lcom/aspose/cells/LoadOptions;)V
    //   17: astore_2
    //   18: aload_2
    //   19: invokevirtual 16	com/aspose/cells/zalq:c	()V
    //   22: aload_0
    //   23: invokevirtual 14	com/aspose/cells/Workbook:getSettings	()Lcom/aspose/cells/WorkbookSettings;
    //   26: iconst_0
    //   27: putfield 12	com/aspose/cells/WorkbookSettings:f	Z
    //   30: aload_0
    //   31: getfield 11	com/aspose/cells/Workbook:a	Lcom/aspose/cells/zqw;
    //   34: getfield 13	com/aspose/cells/zqw:a	Lcom/aspose/cells/zqr;
    //   37: invokevirtual 18	com/aspose/cells/zqr:a	()V
    //   40: aload_2
    //   41: ifnull +39 -> 80
    //   44: aload_2
    //   45: invokevirtual 17	com/aspose/cells/zalq:dispose	()V
    //   48: goto +32 -> 80
    //   51: astore_3
    //   52: aload_0
    //   53: invokevirtual 14	com/aspose/cells/Workbook:getSettings	()Lcom/aspose/cells/WorkbookSettings;
    //   56: iconst_0
    //   57: putfield 12	com/aspose/cells/WorkbookSettings:f	Z
    //   60: aload_0
    //   61: getfield 11	com/aspose/cells/Workbook:a	Lcom/aspose/cells/zqw;
    //   64: getfield 13	com/aspose/cells/zqw:a	Lcom/aspose/cells/zqr;
    //   67: invokevirtual 18	com/aspose/cells/zqr:a	()V
    //   70: aload_2
    //   71: ifnull +7 -> 78
    //   74: aload_2
    //   75: invokevirtual 17	com/aspose/cells/zalq:dispose	()V
    //   78: aload_3
    //   79: athrow
    //   80: return
    // Local variable table:
    //   start	length	slot	name	signature
    //   0	81	0	paramWorkbook	Workbook
    //   0	81	1	paramLoadOptions	LoadOptions
    //   17	58	2	localzalq	zalq
    //   51	28	3	localObject	Object
    // Exception table:
    //   from	to	target	type
    //   18	22	51	finally
  }
}


/* Location:              /media/peter/Data/gitworkspace/github/jxls_demo/libs/aspose-cells-17.10.jar!/com/aspose/cells/zalp.class
 * Java compiler version: 6 (50.0)
 * JD-Core Version:       0.7.1
 */